thepulse/__init__.py
thepulse/auth.py
thepulse/utils.py
thepulse-1.0.7.dist-info/METADATA
thepulse-1.0.7.dist-info/WHEEL
thepulse-1.0.7.dist-info/top_level.txt
thepulse-1.0.7.dist-info/RECORD
