Metadata-Version: 2.1
Name: thepulse
Version: 1.0.7
Summary: Simple Python client library for https://devnull.cn/pulse
Home-page: https://github.com/xizhendu/thepulse-sdk-python
Author: Xizhen Du
Author-email: xizhendu@gmail.com
Requires-Dist: requests
